jlkutils/__init__.py
jlkutils/ai.py
jlkutils/cam.py
jlkutils/chatgpt.py
jlkutils/crypt.py
jlkutils/file.py
jlkutils/jlkutils.py
jlkutils/json.py
jlkutils/utils.py
jlkutils/web.py
jlkutils-0.41.dist-info/METADATA
jlkutils-0.41.dist-info/WHEEL
jlkutils-0.41.dist-info/top_level.txt
jlkutils-0.41.dist-info/RECORD
