Metadata-Version: 2.1
Name: jlkutils
Version: 0.41
Summary: Praktischer Stuff
Classifier: Programming Language :: Python :: 3
Classifier: License :: OSI Approved :: MIT License
Classifier: Operating System :: OS Independent
Requires-Python: >=3.6
Requires-Dist: os
